omegaconf/__init__.py
omegaconf/_impl.py
omegaconf/_utils.py
omegaconf/base.py
omegaconf/basecontainer.py
omegaconf/dictconfig.py
omegaconf/errors.py
omegaconf/grammar_parser.py
omegaconf/grammar_visitor.py
omegaconf/listconfig.py
omegaconf/nodes.py
omegaconf/omegaconf.py
omegaconf/py.typed
omegaconf/version.py
omegaconf/grammar/__init__.py
omegaconf/grammar/gen/OmegaConfGrammarLexer.py
omegaconf/grammar/gen/OmegaConfGrammarParser.py
omegaconf/grammar/gen/OmegaConfGrammarParserListener.py
omegaconf/grammar/gen/OmegaConfGrammarParserVisitor.py
omegaconf/grammar/gen/__init__.py
omegaconf/resolvers/__init__.py
omegaconf/resolvers/oc/__init__.py
omegaconf/resolvers/oc/dict.py
pydevd_plugins/__init__.py
pydevd_plugins/extensions/__init__.py
pydevd_plugins/extensions/pydevd_plugin_omegaconf.py
omegaconf-2.2.3.dist-info/LICENSE
omegaconf-2.2.3.dist-info/METADATA
omegaconf-2.2.3.dist-info/WHEEL
omegaconf-2.2.3.dist-info/top_level.txt
omegaconf-2.2.3.dist-info/RECORD
