Metadata-Version: 2.1
Name: omegaconf
Version: 2.2.3
Summary: A flexible configuration library
Home-page: https://github.com/omry/omegaconf
Author: Omry Yadan
Author-email: omry@yadan.net
Keywords: yaml configuration config
Classifier: Programming Language :: Python :: 3.6
Classifier: Programming Language :: Python :: 3.7
Classifier: Programming Language :: Python :: 3.8
Classifier: Programming Language :: Python :: 3.9
Classifier: Programming Language :: Python :: 3.10
Classifier: License :: OSI Approved :: BSD License
Classifier: Operating System :: OS Independent
Requires-Python: >=3.6
License-File: LICENSE
